discord/ext/forms/__init__.py
discord/ext/forms/form.py
discord/ext/forms/helpers.py
discord/ext/forms/reactions.py
discord_ext_forms-3.0.3.dist-info/LICENSE
discord_ext_forms-3.0.3.dist-info/METADATA
discord_ext_forms-3.0.3.dist-info/WHEEL
discord_ext_forms-3.0.3.dist-info/top_level.txt
discord_ext_forms-3.0.3.dist-info/RECORD
