Metadata-Version: 2.1
Name: discord-ext-forms
Version: 3.0.3
Summary: Easy forms and surveys for discord.py.
Home-page: https://github.com/terabyte3/discord-ext-forms
Author: terabyte3
Author-email: terabyte@terabyteis.me
License: MIT
Platform: UNKNOWN
Classifier: Programming Language :: Python :: 3.7
Classifier: Programming Language :: Python :: 3.8
Classifier: Programming Language :: Python :: 3.9
Classifier: License :: OSI Approved :: MIT License
Classifier: Operating System :: OS Independent
Classifier: Topic :: Communications :: Chat
Classifier: Intended Audience :: Developers
Requires-Python: >=3.7
License-File: LICENSE
Requires-Dist: discord.py (>=1.5)
Requires-Dist: emoji
